lzsr_math/__init__.py
lzsr_math/lzsr_series.py
lzsr_math/setup.py
lzsr_math-1.7.9.dist-info/LICENSE
lzsr_math-1.7.9.dist-info/METADATA
lzsr_math-1.7.9.dist-info/WHEEL
lzsr_math-1.7.9.dist-info/top_level.txt
lzsr_math-1.7.9.dist-info/RECORD
