Metadata-Version: 2.1
Name: lzsr-math
Version: 1.7.9
Summary: The Python package can help you simplify some code in programming.
Home-page: https://github.com/lzsr/lzsr
Author: lzsr
Author-email: y15305083929@outlook.com
License: UNKNOWN
Platform: UNKNOWN
Classifier: Programming Language :: Python :: 3
Classifier: License :: OSI Approved :: MIT License
Classifier: Operating System :: OS Independent
Requires-Python: >=3.6
